darwinpush
