Metadata-Version: 1.1
Name: hp-darwinpush
Version: 0.0.3
Summary: HackPartners Darwinpush
Home-page: https://github.com/hackpartners/darwinpush
Author: HackPartners
Author-email: dev@hackpartners.com
License: MIT
Keywords: uk rail darwin push
Platform: UNKNOWN
Classifier: Development Status :: 3 - Alpha
Classifier: Intended Audience :: Developers
Classifier: Topic :: Software Development
Classifier: License :: OSI Approved :: Apache Software License
Classifier: Programming Language :: Python :: 3
Classifier: Programming Language :: Python :: 3.4
